admin_ip_restrictor/__init__.py
admin_ip_restrictor/middleware.py
django_admin_ip_restrictor-1.0.0.dist-info/LICENSE
django_admin_ip_restrictor-1.0.0.dist-info/METADATA
django_admin_ip_restrictor-1.0.0.dist-info/WHEEL
django_admin_ip_restrictor-1.0.0.dist-info/top_level.txt
django_admin_ip_restrictor-1.0.0.dist-info/RECORD
