Metadata-Version: 2.1
Name: django-admin-ip-restrictor
Version: 1.0.0
Summary: A Django middleware to restrict incoming IPs to admin panel
Home-page: https://github.com/sdonk/django-admin-ip-restrictor/
Author: Alessandro De Noia
Author-email: alessandro.denoia@gmail.com
License: MIT License
Platform: UNKNOWN
Classifier: Development Status :: 5 - Production/Stable
Classifier: Environment :: Web Environment
Classifier: Framework :: Django
Classifier: Framework :: Django :: 1.10
Classifier: Framework :: Django :: 1.11
Classifier: Framework :: Django :: 2.0
Classifier: Intended Audience :: Developers
Classifier: License :: OSI Approved :: MIT License
Classifier: Operating System :: OS Independent
Classifier: Programming Language :: Python
Classifier: Programming Language :: Python :: 3.4
Classifier: Programming Language :: Python :: 3.5
Classifier: Programming Language :: Python :: 3.6
Classifier: Topic :: Software Development :: Libraries :: Python Modules
Requires-Dist: django (>=1.9)
Requires-Dist: django-ipware (<3,>=2)
Provides-Extra: tests
Requires-Dist: coverage (==4.4.2); extra == 'tests'
Requires-Dist: pytest (==3.2.3); extra == 'tests'
Requires-Dist: pytest-cov (==2.5.1); extra == 'tests'
Requires-Dist: pytest-django (==3.1.2); extra == 'tests'
Requires-Dist: pytest-sugar (==0.9.0); extra == 'tests'
Requires-Dist: tox (==2.9.1); extra == 'tests'
